Metadata-Version: 2.1
Name: notebook-prototyping
Version: 0.1.11
Home-page: https://github.com/rlhjansen/nbprototyping
Author: Reitze Jansen
Author-email: rlh.jansen@outlook.com
License: MIT
Keywords: jupyter notebook,tooling
License-File: LICENSE
